fastapi_oauth/__init__.py
fastapi_oauth/common/__init__.py
fastapi_oauth/common/context.py
fastapi_oauth/common/deps.py
fastapi_oauth/common/encoding.py
fastapi_oauth/common/errors.py
fastapi_oauth/common/security.py
fastapi_oauth/common/setting.py
fastapi_oauth/common/types.py
fastapi_oauth/common/urls.py
fastapi_oauth/rfc6749/__init__.py
fastapi_oauth/rfc6749/authenticate_client.py
fastapi_oauth/rfc6749/authorization_server.py
fastapi_oauth/rfc6749/errors.py
fastapi_oauth/rfc6749/grants/__init__.py
fastapi_oauth/rfc6749/grants/authorization_code.py
fastapi_oauth/rfc6749/grants/base.py
fastapi_oauth/rfc6749/grants/client_credentials.py
fastapi_oauth/rfc6749/grants/implicit.py
fastapi_oauth/rfc6749/grants/refresh_token.py
fastapi_oauth/rfc6749/grants/resource_owner_password_credentials.py
fastapi_oauth/rfc6749/mixins.py
fastapi_oauth/rfc6749/models.py
fastapi_oauth/rfc6749/parameters.py
fastapi_oauth/rfc6749/resource_protector.py
fastapi_oauth/rfc6749/signals.py
fastapi_oauth/rfc6749/token_endpoint.py
fastapi_oauth/rfc6749/util.py
fastapi_oauth/rfc6749/wrappers.py
fastapi_oauth/rfc6750/__init__.py
fastapi_oauth/rfc6750/errors.py
fastapi_oauth/rfc6750/parameters.py
fastapi_oauth/rfc6750/token.py
fastapi_oauth/rfc6750/validator.py
fastapi_oauth/rfc7009/__init__.py
fastapi_oauth/rfc7009/parameters.py
fastapi_oauth/rfc7009/revocation.py
fastapi_oauth/rfc7636/__init__.py
fastapi_oauth/rfc7636/challenge.py
fastapi_oauth/utils/__init__.py
fastapi_oauth/utils/consts.py
fastapi_oauth/utils/functions.py
fastapi_oauth-0.3.3.dist-info/LICENSE
fastapi_oauth-0.3.3.dist-info/WHEEL
fastapi_oauth-0.3.3.dist-info/METADATA
fastapi_oauth-0.3.3.dist-info/RECORD
